traymenu/LICENSE
traymenu/README.MD
traymenu/__init__.py
traymenu/requirements.txt
traymenu/thirdparty.json
traymenu-0.10.dist-info/LICENSE.rst
traymenu-0.10.dist-info/METADATA
traymenu-0.10.dist-info/WHEEL
traymenu-0.10.dist-info/top_level.txt
traymenu-0.10.dist-info/RECORD
