Metadata-Version: 2.1
Name: traymenu
Version: 0.10
Summary: System Tray Menu for Windows - no dependencies
Home-page: https://github.com/hansalemaos/traymenu
Author: Johannes Fischer
Author-email: <aulasparticularesdealemaosp@gmail.com>
License: MIT
Keywords: ctypes,windows,toast,tray
Classifier: Development Status :: 4 - Beta
Classifier: Programming Language :: Python :: 3 :: Only
Classifier: Programming Language :: Python :: 3.10
Classifier: Topic :: Scientific/Engineering :: Visualization
Classifier: Topic :: Software Development :: Libraries :: Python Modules
Classifier: Topic :: Utilities
License-File: LICENSE.rst
